cardilib/__init__.py
cardilib/analysis/__init__.py
cardilib/analysis/dyssynchrony_analysis.py
cardilib/analysis/peak_given.py
cardilib/analysis/peaks_calculation.py
cardilib/analysis/statistical_functions.py
cardilib/analysis/.ipynb_checkpoints/peak_given-checkpoint.py
cardilib/analysis/.ipynb_checkpoints/peaks_calculation-checkpoint.py
cardilib/image/__init__.py
cardilib/image/image_data.py
cardilib-0.0.3.dist-info/AUTHORS.rst
cardilib-0.0.3.dist-info/LICENSE.txt
cardilib-0.0.3.dist-info/METADATA
cardilib-0.0.3.dist-info/WHEEL
cardilib-0.0.3.dist-info/top_level.txt
cardilib-0.0.3.dist-info/RECORD
