Metadata-Version: 2.1
Name: cardilib
Version: 0.0.3
Summary: Python library for performing biomedical images analysis
Home-page: https://github.com/CardiAP/cardilib
Author: Velez Rueda Ana Julia
Author-email: anavelezrueda@gmail.com
License: UNKNOWN
Project-URL: Bug Tracker, https://github.com/CardiAP/cardilib/issues
Platform: UNKNOWN
Classifier: Programming Language :: Python :: 3
Classifier: License :: OSI Approved :: MIT License
Classifier: Operating System :: OS Independent
License-File: LICENSE.txt
License-File: AUTHORS.rst
Requires-Dist: importlib-metadata
Requires-Dist: numpy (~=1.21)
Requires-Dist: opencv-python (~=4.5.2)
Requires-Dist: PeakUtils (~=1.3)
Provides-Extra: testing
Requires-Dist: setuptools ; extra == 'testing'
Requires-Dist: pytest ; extra == 'testing'
Requires-Dist: pytest-cov ; extra == 'testing'
